medium_to_ghost/image_downloader.py
medium_to_ghost/medium_post_parser.py
medium_to_ghost/medium_to_ghost.py
medium_to_ghost-0.0.4.dist-info/LICENSE
medium_to_ghost-0.0.4.dist-info/METADATA
medium_to_ghost-0.0.4.dist-info/WHEEL
medium_to_ghost-0.0.4.dist-info/entry_points.txt
medium_to_ghost-0.0.4.dist-info/top_level.txt
medium_to_ghost-0.0.4.dist-info/RECORD
