Metadata-Version: 2.1
Name: medium-to-ghost
Version: 0.0.4
Summary: Convert a Medium blog export file to Ghost 2.0 format (including images)
Home-page: https://github.com/ageitgey/medium_to_ghost
Author: Adam Geitgey
Author-email: ageitgey@gmail.com
License: MIT license
Keywords: Medium
Platform: UNKNOWN
Classifier: Development Status :: 4 - Beta
Classifier: Intended Audience :: Developers
Classifier: License :: OSI Approved :: MIT License
Classifier: Natural Language :: English
Classifier: Programming Language :: Python :: 3.6
Classifier: Programming Language :: Python :: 3.7
Requires-Dist: beautifulsoup4
Requires-Dist: Click (>=6.0)
